eebd_gesam2-0.2.0.dist-info/licenses/LICENSE
sam2_annotator/__init__.py
sam2_annotator/app.py
sam2_annotator/main.py
sam2_annotator/configs/sam2_hiera_l.yaml
eebd_gesam2-0.2.0.dist-info/METADATA
eebd_gesam2-0.2.0.dist-info/WHEEL
eebd_gesam2-0.2.0.dist-info/entry_points.txt
eebd_gesam2-0.2.0.dist-info/top_level.txt
eebd_gesam2-0.2.0.dist-info/RECORD
