Metadata-Version: 2.4
Name: EEBD-GESAM2
Version: 0.2.0
Summary: 一个基于 SAM2 和 Tkinter 的交互式图像分割与标注工具。
Author-email: Yaopeng Han <hanyp@qibebt.ac.cn>
License: MIT License
Project-URL: Homepage, https://github.com/your-username/your-repo
Project-URL: Bug Tracker, https://github.com/your-username/your-repo/issues
Keywords: sam,sam2,segmentation,annotation,gui,tkinter,pytorch,labelme
Classifier: Development Status :: 4 - Beta
Classifier: Programming Language :: Python :: 3
Classifier: Programming Language :: Python :: 3.8
Classifier: Programming Language :: Python :: 3.9
Classifier: Programming Language :: Python :: 3.10
Classifier: Programming Language :: Python :: 3.11
Classifier: License :: OSI Approved :: MIT License
Classifier: Operating System :: OS Independent
Classifier: Topic :: Scientific/Engineering :: Image Recognition
Classifier: Intended Audience :: Developers
Classifier: Intended Audience :: Science/Research
Requires-Python: >=3.8
License-File: LICENSE
Requires-Dist: torch>=1.8
Requires-Dist: numpy
Requires-Dist: Pillow
Requires-Dist: opencv-python
Requires-Dist: appdirs>=1.4.4
Dynamic: license-file
